python_github_plus/__init__.py
python_github_plus/github_plus.py
python_github_plus-0.0.4.dist-info/licenses/LICENSE
python_github_plus-0.0.4.dist-info/METADATA
python_github_plus-0.0.4.dist-info/WHEEL
python_github_plus-0.0.4.dist-info/top_level.txt
python_github_plus-0.0.4.dist-info/RECORD
