Metadata-Version: 2.4
Name: python-github-plus
Version: 0.0.4
Summary: Enhanced Python GitHub client.
Home-page: https://github.com/aviz92/python-github-plus
Author: Avi Zaguri
Author-email: 
Project-URL: Repository, https://github.com/aviz92/python-github-plus
Requires-Python: >=3.11
License-File: LICENSE
Requires-Dist: setuptools
Requires-Dist: wheel
Requires-Dist: python-dotenv
Requires-Dist: pre-commit
Requires-Dist: pytest
Requires-Dist: pygithub
Requires-Dist: custom-python-logger
Dynamic: author
Dynamic: description
Dynamic: description-content-type
Dynamic: home-page
Dynamic: license-file
Dynamic: project-url
Dynamic: requires-dist
Dynamic: requires-python
Dynamic: summary
